spg_style/__init__.py
spg_style/spg_style.py
spg_style-0.1.2.dist-info/METADATA
spg_style-0.1.2.dist-info/WHEEL
spg_style-0.1.2.dist-info/RECORD
