Metadata-Version: 2.1
Name: spg_style
Version: 0.1.2
Summary: S&P Global charting style according to EDP style guideline
Author: Kunfeng
Author-email: kovkov@163.com
Requires-Python: >=3.12,<4.0
Classifier: Programming Language :: Python :: 3
Classifier: Programming Language :: Python :: 3.12
Classifier: Programming Language :: Python :: 3.13
Requires-Dist: matplotlib (>=3.10.8,<4.0.0)
Requires-Dist: pandas (>=3.0.0,<4.0.0)
Requires-Dist: python-pptx (>=1.0.2,<2.0.0)
